rtl/fir.sv
module fir #(parameter logic [31:0] BITS = 8, TAPS = 4) (
	input clk,
	input rst_n,
	input start,
	input coeff_load_in,
	input coeff_in,
	input [BITS-1:0] x,
	output reg [BITS-1:0] y
);

localparam logic [31:0] TAPS_HALF = TAPS >> 1;
localparam logic [31:0] SAMPLE_CNT_BITS = $clog2(TAPS_HALF);
localparam logic [31:0] BITS_CNT_BITS = $clog2(BITS);

// control signals
logic sft, sample_cnt_en, bit_cnt_en, mac_en, sample_cnt_rst;

integer i;
integer j;
// samples LSFR
reg [TAPS-1:0] [BITS-1:0] samples;
always_ff @(posedge clk) begin
	// reset
	if (!rst_n) begin
		for (i = 0; i < TAPS; i=i+1) begin
			samples[i] <= 'd0;
		end
	// shifting
	end else begin
		if (start) begin
			for (i = TAPS - 1; i > 0; i = i - 1) begin
				samples[i] <= samples[i-1];
			end
			samples[0] <= x;
		end else if (sft) begin
			samples[0] <= samples[TAPS_HALF - 1];
			samples[TAPS_HALF] <= samples[TAPS - 1];
			for (i = TAPS_HALF - 1; i > 0; i = i - 1) begin
				samples[i] <= samples[i-1];
			end
			for (j = TAPS - 1; j > TAPS_HALF; j = j - 1) begin
				samples[j] <= samples[j-1];
			end
		end
	end
end

integer k;
// coefficients LSFR
reg [TAPS_HALF-1:0] [BITS-1:0] coeffs;
always_ff @(posedge clk) begin
	// reset
	if (!rst_n) begin
		for (k = 0; k < TAPS_HALF; k = k + 1) begin
			coeffs[k] <= 'd0;
		end
	// shifting
	end else begin
		if (coeff_load_in) begin
			coeffs[0][0] <= coeff_in;
			for (k = BITS - 1; k > 0; k = k - 1) begin
				coeffs[0][k] <= coeffs[0][k-1];
			end
		end else if (sft) begin
			coeffs[0] <= coeffs[TAPS_HALF - 1];
			for (k = TAPS_HALF - 1; k > 0; k = k - 1) begin
				coeffs[k] <= coeffs[k-1];
			end
		end
	end
end

// sample counter
reg [SAMPLE_CNT_BITS-1:0] sample_cnt;
always_ff @(posedge clk) begin
	if (!rst_n) begin
		sample_cnt <= 'd0;
	end
	else begin
		if (sample_cnt_en) begin
			sample_cnt <= sample_cnt + 1'b1;
		end else if (sample_cnt_rst) begin
			sample_cnt <= 'd0;
		end
	end
end

// bit counter
reg [BITS_CNT_BITS-1:0] bit_cnt;
always_ff @(posedge clk) begin
	if (!rst_n) begin
		bit_cnt <= 'd0;
	end
	else begin
		if ((bit_cnt_en == 1'b1) && (bit_cnt < BITS-1)) begin
			bit_cnt <= bit_cnt + 1'b1;
		end else begin
			bit_cnt <= 'd0;
		end
	end
end

// MAC: Multiply and Accumulate
logic [1:0] sel;
logic [BITS-1:0] currCoeff;
logic [BITS-1:0] currCoeff2;
logic [BITS-1:0] mux_out;
logic [BITS-1:0] acc_in;
always_comb begin
	// create select signal through filter symmetry
	sel = samples[0][bit_cnt] + samples[TAPS-1][bit_cnt];
	currCoeff = coeffs[0] << bit_cnt;
	currCoeff2 = currCoeff << 1;
	// MUX`
	case (sel)
		2'b00: mux_out = 'd0;
		2'b01: mux_out = currCoeff;
		2'b10: mux_out = currCoeff2;
	endcase
	acc_in = y + mux_out;
end

// accumulator register
always_ff @(posedge clk) begin
	if (!rst_n) begin
		y <= 'd0;
	end
	else begin
		if (start) begin
			y <= 'd0;
		end else if (mac_en) begin
			y <= acc_in;
		end
	end
end

// STATE MACHINE
typedef enum logic [1:0] {
    IDLE,
    COEFF_LD,
	OP,
    SHIFT
  } STATE_DEF;
STATE_DEF n_state, state;
// transition states
always_ff @(posedge clk) begin
    if (!rst_n) begin
		state <= IDLE;
    end else begin
		state <= n_state;
    end
end

// next state
always_comb begin
	case (state)
		IDLE: begin
			if (start) n_state = OP;
			else if (coeff_load_in) n_state = COEFF_LD;
			else n_state = IDLE;
		end
		COEFF_LD: begin
			if (coeff_load_in) n_state = COEFF_LD;
			else n_state = IDLE;
		end
		OP: begin
			if (bit_cnt < BITS-2) n_state = OP;
			else n_state = SHIFT;
		end
		SHIFT: begin
			if (sample_cnt < TAPS_HALF - 1) n_state = OP;
			else n_state = IDLE;
		end
	endcase
end

// control signals
always_comb begin
	sft = 1'b0;
	sample_cnt_en = 1'b0;
	bit_cnt_en = 1'b0;
	mac_en = 1'b0;
	sample_cnt_rst = 1'b0;
	case (state)
		IDLE: begin
			sample_cnt_rst = 1'b1;
		end
//		COEFF_LD: begin
//			
//		end
		OP: begin
			mac_en = 1'b1;
			bit_cnt_en = 1'b1;
		end
		SHIFT: begin
			sft = 1'b1;
			mac_en = 1'b1;
			bit_cnt_en = 1'b1;
			sample_cnt_en = 1'b1;
		end
	endcase
end

endmodule

sim/firtb.sv
`timescale 1ns/1ps

module firtb;

   parameter BITS = 8;
   parameter TAPS = 4;

   reg clk, rst_n, start;
   reg [BITS-1:0] x;
   wire [BITS-1:0] y;

   always #5 clk = ~clk;

   initial begin
      clk = 0;
      #5;
      rst_n = 0;
      #12;
      rst_n = 1;
   end

   int n;

   fir #(.BITS(BITS), .TAPS(TAPS)) DUT (
      .clk(clk),
      .rst_n(rst_n),
      .start(start),
      .x(x),
      .y(y)
   );

   initial begin
      x = 'd0;
      start = 1'b0;

      $dumpfile("trace.vcd");
      $dumpvars(0, firtb);

      @(posedge rst_n);

      // shift samples in
      for (n = 0; n < 20; n = n + 1) begin
		repeat(2) begin
			@(negedge clk);
			start = ~start;
		end

        $display("X %x, Y %x", x, y);

		@(negedge clk);
        x = $random();
      end

      $finish();
   end

endmodule

sim/trace.vcd
$date
    Oct  4, 2024  16:36:32
$end
$version
    TOOL:	xmsim	22.09-s011
$end
$timescale
    1 ps
$end

$scope module firtb $end
$var parameter 32 !    BITS $end
$var parameter 32 "    TAPS $end
$var reg       1 #    clk $end
$var reg       1 $    rst_n $end
$var reg       1 %    start $end
$var reg       8 &    x [7:0] $end
$var wire      8 '    y [7:0] $end
$var integer  32 (    n $end

$scope module DUT $end
$var parameter 32 )    BITS $end
$var parameter 32 *    TAPS $end
$var wire      1 +    clk  $end
$var wire      1 ,    rst_n  $end
$var wire      1 -    start  $end
$var wire      8 .    x [7:0] $end
$var wire      8 '    y [7:0] $end
$var reg       8 /    samples[0] [7:0] $end
$var reg       8 0    samples[1] [7:0] $end
$var reg       8 1    samples[2] [7:0] $end
$var reg       8 2    samples[3] [7:0] $end
$var integer  32 3    i $end
$upscope $end

$upscope $end

$enddefinitions $end
$dumpvars
b100 *
b1000 )
b100 "
b1000 !
0#
x$
0%
b0 &
bx '
b0 (
0+
x,
0-
b0 .
bx /
bx 0
bx 1
bx 2
bx 3
$end
#5000
1#
0$
0,
1+
b0 3
b1 3
b10 3
b11 3
b100 3
b0 /
b0 0
b0 1
b0 2
b0 '
#10000
0#
0+
#15000
1#
1+
b0 3
b1 3
b10 3
b11 3
b100 3
#17000
1$
1,
#20000
0#
1%
1-
0+
#25000
1#
1+
b11 3
b10 3
b1 3
b0 3
#30000
0#
0%
0-
0+
#35000
1#
1+
#40000
0#
b100100 &
b1 (
b100100 .
0+
#45000
1#
1+
#50000
0#
1%
1-
0+
#55000
1#
1+
b11 3
b10 3
b1 3
b0 3
b100100 /
#60000
0#
0%
0-
0+
#65000
1#
1+
#70000
0#
b10000001 &
b10 (
b10000001 .
0+
#75000
1#
1+
#80000
0#
1%
1-
0+
#85000
1#
1+
b11 3
b10 3
b1 3
b0 3
b100100 0
b10000001 /
#90000
0#
0%
0-
0+
#95000
1#
1+
#100000
0#
b1001 &
b11 (
b1001 .
0+
#105000
1#
1+
#110000
0#
1%
1-
0+
#115000
1#
1+
b11 3
b10 3
b1 3
b0 3
b100100 1
b10000001 0
b1001 /
#120000
0#
0%
0-
0+
#125000
1#
1+
#130000
0#
b1100011 &
b100 (
b1100011 .
0+
#135000
1#
1+
#140000
0#
1%
1-
0+
#145000
1#
1+
b11 3
b10 3
b1 3
b0 3
b100100 2
b10000001 1
b1001 0
b1100011 /
b100100 '
#150000
0#
0%
0-
0+
#155000
1#
1+
#160000
0#
b1101 &
b101 (
b1101 .
0+
#165000
1#
1+
#170000
0#
1%
1-
0+
#175000
1#
1+
b11 3
b10 3
b1 3
b0 3
b10000001 2
b1001 1
b1100011 0
b1101 /
b10000001 '
#180000
0#
0%
0-
0+
#185000
1#
1+
#190000
0#
b10001101 &
b110 (
b10001101 .
0+
#195000
1#
1+
#200000
0#
1%
1-
0+
#205000
1#
1+
b11 3
b10 3
b1 3
b0 3
b1001 2
b1100011 1
b1101 0
b10001101 /
b1001 '
#210000
0#
0%
0-
0+
#215000
1#
1+
#220000
0#
b1100101 &
b111 (
b1100101 .
0+
#225000
1#
1+
#230000
0#
1%
1-
0+
#235000
1#
1+
b11 3
b10 3
b1 3
b0 3
b1100011 2
b1101 1
b10001101 0
b1100101 /
b1100011 '
#240000
0#
0%
0-
0+
#245000
1#
1+
#250000
0#
b10010 &
b1000 (
b10010 .
0+
#255000
1#
1+
#260000
0#
1%
1-
0+
#265000
1#
1+
b11 3
b10 3
b1 3
b0 3
b1101 2
b10001101 1
b1100101 0
b10010 /
b1101 '
#270000
0#
0%
0-
0+
#275000
1#
1+
#280000
0#
b1 &
b1001 (
b1 .
0+
#285000
1#
1+
#290000
0#
1%
1-
0+
#295000
1#
1+
b11 3
b10 3
b1 3
b0 3
b10001101 2
b1100101 1
b10010 0
b1 /
b10001101 '
#300000
0#
0%
0-
0+
#305000
1#
1+
#310000
0#
b1101 &
b1010 (
b1101 .
0+
#315000
1#
1+
#320000
0#
1%
1-
0+
#325000
1#
1+
b11 3
b10 3
b1 3
b0 3
b1100101 2
b10010 1
b1 0
b1101 /
b1100101 '
#330000
0#
0%
0-
0+
#335000
1#
1+
#340000
0#
b1110110 &
b1011 (
b1110110 .
0+
#345000
1#
1+
#350000
0#
1%
1-
0+
#355000
1#
1+
b11 3
b10 3
b1 3
b0 3
b10010 2
b1 1
b1101 0
b1110110 /
b10010 '
#360000
0#
0%
0-
0+
#365000
1#
1+
#370000
0#
b111101 &
b1100 (
b111101 .
0+
#375000
1#
1+
#380000
0#
1%
1-
0+
#385000
1#
1+
b11 3
b10 3
b1 3
b0 3
b1 2
b1101 1
b1110110 0
b111101 /
b1 '
#390000
0#
0%
0-
0+
#395000
1#
1+
#400000
0#
b11101101 &
b1101 (
b11101101 .
0+
#405000
1#
1+
#410000
0#
1%
1-
0+
#415000
1#
1+
b11 3
b10 3
b1 3
b0 3
b1101 2
b1110110 1
b111101 0
b11101101 /
b1101 '
#420000
0#
0%
0-
0+
#425000
1#
1+
#430000
0#
b10001100 &
b1110 (
b10001100 .
0+
#435000
1#
1+
#440000
0#
1%
1-
0+
#445000
1#
1+
b11 3
b10 3
b1 3
b0 3
b1110110 2
b111101 1
b11101101 0
b10001100 /
b1110110 '
#450000
0#
0%
0-
0+
#455000
1#
1+
#460000
0#
b11111001 &
b1111 (
b11111001 .
0+
#465000
1#
1+
#470000
0#
1%
1-
0+
#475000
1#
1+
b11 3
b10 3
b1 3
b0 3
b111101 2
b11101101 1
b10001100 0
b11111001 /
b111101 '
#480000
0#
0%
0-
0+
#485000
1#
1+
#490000
0#
b11000110 &
b10000 (
b11000110 .
0+
#495000
1#
1+
#500000
0#
1%
1-
0+
#505000
1#
1+
b11 3
b10 3
b1 3
b0 3
b11101101 2
b10001100 1
b11111001 0
b11000110 /
b11101101 '
#510000
0#
0%
0-
0+
#515000
1#
1+
#520000
0#
b11000101 &
b10001 (
b11000101 .
0+
#525000
1#
1+
#530000
0#
1%
1-
0+
#535000
1#
1+
b11 3
b10 3
b1 3
b0 3
b10001100 2
b11111001 1
b11000110 0
b11000101 /
b10001100 '
#540000
0#
0%
0-
0+
#545000
1#
1+
#550000
0#
b10101010 &
b10010 (
b10101010 .
0+
#555000
1#
1+
#560000
0#
1%
1-
0+
#565000
1#
1+
b11 3
b10 3
b1 3
b0 3
b11111001 2
b11000110 1
b11000101 0
b10101010 /
b11111001 '
#570000
0#
0%
0-
0+
#575000
1#
1+
#580000
0#
b11100101 &
b10011 (
b11100101 .
0+
#585000
1#
1+
#590000
0#
1%
1-
0+
#595000
1#
1+
b11 3
b10 3
b1 3
b0 3
b11000110 2
b11000101 1
b10101010 0
b11100101 /
b11000110 '
#600000
0#
0%
0-
0+
#605000
1#
1+
#610000
0#
b1110111 &
b10100 (
